best_ec2/__init__.py
best_ec2/aws_utils.py
best_ec2/best_ec2.py
best_ec2/best_ec2_impl.py
best_ec2/cache.py
best_ec2/constants.py
best_ec2/enrichers.py
best_ec2/exceptions.py
best_ec2/filters.py
best_ec2/spot_utils.py
best_ec2/types.py
best_ec2/utils.py
best_ec2/validators.py
best_ec2/strategies/__init__.py
best_ec2/strategies/abstract_sort_strategy.py
best_ec2/strategies/sort_on_demand_strategy.py
best_ec2/strategies/sort_spot_strategy.py
best_ec2/strategies/sort_strategy_factory.py
best_ec2-1.1.4.dist-info/METADATA
best_ec2-1.1.4.dist-info/WHEEL
best_ec2-1.1.4.dist-info/top_level.txt
best_ec2-1.1.4.dist-info/RECORD
