Metadata-Version: 2.1
Name: best-ec2
Version: 1.1.4
Summary: Best EC2, the smart solution designed to optimize your Amazon EC2 instance type selection process. The app simplifies the challenge of choosing the optimal EC2 instance type that matches your specific requirements, balancing performance, cost, and computing needs.
Home-page: https://gitlab.com/aliaksei-kankou/best-ec2/python-package
Author: Aliaksei Kankou
Author-email: aliaksei.kankou@gmail.com
Requires-Python: >=3.8.0
Requires-Dist: boto3 >=1.29.2
